pcr/__init__.py
pcr/aes.py
pcr/cbc.py
pcr/diffie_hellman.py
pcr/hotp.py
pcr/maths.py
pcr/pbkdf2.py
pcr/pkcs7.py
pcr/rc4.py
pcr/rfc3526.py
pcr/xtea.py
pcr/tests/__init__.py
pcr/tests/test_aes.py
pcr/tests/test_cbc.py
pcr/tests/test_diffie_hellman.py
pcr/tests/test_hotp.py
pcr/tests/test_init.py
pcr/tests/test_maths.py
pcr/tests/test_pbkdf2.py
pcr/tests/test_pkcs7.py
pcr/tests/test_rc4.py
pcr/tests/test_xtea.py
pcr-0.8.0.dist-info/DESCRIPTION.rst
pcr-0.8.0.dist-info/METADATA
pcr-0.8.0.dist-info/metadata.json
pcr-0.8.0.dist-info/RECORD
pcr-0.8.0.dist-info/top_level.txt
pcr-0.8.0.dist-info/WHEEL
