Metadata-Version: 2.0
Name: pcr
Version: 0.8.0
Summary: Python 3 Cryptography Toolkit
Home-page: https://github.com/sfstpala/pcr/
Author: Stefano Palazzo
Author-email: stefano.palazzo@gmail.com
License: GPLv3
Platform: all
Classifier: Programming Language :: Python :: 3
Classifier: License :: OSI Approved :: GNU General Public License v3 or later (GPLv3+)
Classifier: Topic :: Security :: Cryptography
